optvl/MExt.py
optvl/__init__.py
optvl/libavl.cpython-311-x86_64-linux-gnu.so
optvl/om_wrapper.py
optvl/optvl_class.py
optvl/utils/__init__.py
optvl/utils/airfoil_utils.py
optvl/utils/check_surface_dict.py
optvl.libs/libgfortran-040039e1.so.5.0.0
optvl.libs/libquadmath-96973f99.so.0.0.0
optvl-2.2.2.dist-info/LICENSE.txt
optvl-2.2.2.dist-info/METADATA
optvl-2.2.2.dist-info/WHEEL
optvl-2.2.2.dist-info/RECORD
