Metadata-Version: 2.1
Name: optvl
Version: 2.2.2
Summary: A modified version of Mark Drela and Harold Youngren's famous AVL code with a direct Python interface and gradient based optimization support.
License: ----
Project-URL: homepage, https://github.com/joanibal/OptVL
Project-URL: source, https://github.com/joanibal/OptVL
Project-URL: tracker, https://github.com/joanibal/OptVL/issues
Requires-Dist: numpy>=1.19
